{
  "rootCauseHypothesis": "The form submission is likely reaching a backend endpoint that is failing or never resolving on the hosting side, so the client stays in the pending state. Common causes include a broken serverless function, database connection/authentication issue, missing environment variables, runtime crash after submit, or a response that is not returned correctly, preventing the success confirmation from appearing. Underlying error: TEST FAILURE\n\nSaving the borrowing record did not complete — the form submission remained stuck and no success confirmation appeared.\n\nObservations:\n- The 'Simpan Peminjaman' button is disabled and displays 'Menyimpan...' (indicating submission in progress).\n- No success message 'Peminjaman Berhasil Dicatat' appeared after multiple waits and searches.\n- The page remained on the 'Form Peminjaman Arsip' with input values still present (submission not acknowledged).",
  "recommendedFixTarget": {
    "kind": "env",
    "reference": "Simpan Peminjaman",
    "rationale": "Inspect the server action/API handler used by 'Simpan Peminjaman' and fix any request timeout, thrown exception, or broken backend write path so it returns a success response. Check hosting logs for 4xx/5xx errors, ensure the database/connection string and environment variables are correct, and verify the endpoint completes and sends the success message/redirect so the UI can leave the 'Menyimpan...' state."
  },
  "evidence": []
}
